pygekko/__init__.py
pygekko/_internals.py
pygekko/core.py
pygekko/interface.py
pygekko/settings.py
pygekko/type_checks.py
pygekko/utils.py
pygekko/native/win-x64/ANTLR.dll
pygekko/native/win-x64/AngouriMath.dll
pygekko/native/win-x64/Antlr3.Runtime.dll
pygekko/native/win-x64/Antlr4.Runtime.Standard.dll
pygekko/native/win-x64/Apache.Arrow.dll
pygekko/native/win-x64/AutomaticGraphLayout.Drawing.dll
pygekko/native/win-x64/AutomaticGraphLayout.dll
pygekko/native/win-x64/EPPlus.dll
pygekko/native/win-x64/GAMS.net4.dll
pygekko/native/win-x64/Gekko.exe
pygekko/native/win-x64/Gekko.exe.config
pygekko/native/win-x64/Gekko.ico
pygekko/native/win-x64/Gekko.lnk
pygekko/native/win-x64/Gekko.pdb
pygekko/native/win-x64/GekkoFlowChart.exe
pygekko/native/win-x64/GenericTensor.dll
pygekko/native/win-x64/HonkSharp.dll
pygekko/native/win-x64/IndexRange.dll
pygekko/native/win-x64/Interop.IWshRuntimeLibrary.dll
pygekko/native/win-x64/IronCompress.dll
pygekko/native/win-x64/MathNet.Numerics.dll
pygekko/native/win-x64/Microsoft.Bcl.AsyncInterfaces.dll
pygekko/native/win-x64/Microsoft.Data.Analysis.dll
pygekko/native/win-x64/Microsoft.IO.RecyclableMemoryStream.dll
pygekko/native/win-x64/Microsoft.ML.DataView.dll
pygekko/native/win-x64/Microsoft.Msagl.WpfGraphControl.dll
pygekko/native/win-x64/Microsoft.Win32.Primitives.dll
pygekko/native/win-x64/Numbers.dll
pygekko/native/win-x64/Parquet.dll
pygekko/native/win-x64/Snappier.dll
pygekko/native/win-x64/System.AppContext.dll
pygekko/native/win-x64/System.Buffers.dll
pygekko/native/win-x64/System.Collections.Concurrent.dll
pygekko/native/win-x64/System.Collections.Immutable.dll
pygekko/native/win-x64/System.Collections.NonGeneric.dll
pygekko/native/win-x64/System.Collections.Specialized.dll
pygekko/native/win-x64/System.Collections.dll
pygekko/native/win-x64/System.ComponentModel.Annotations.dll
pygekko/native/win-x64/System.ComponentModel.EventBasedAsync.dll
pygekko/native/win-x64/System.ComponentModel.Primitives.dll
pygekko-3.3.2.post1.dist-info/METADATA
pygekko-3.3.2.post1.dist-info/WHEEL
pygekko-3.3.2.post1.dist-info/licenses/LICENCE
pygekko-3.3.2.post1.dist-info/RECORD
