Metadata-Version: 2.4
Name: pygekko
Version: 3.3.2.post1
Summary: PyGekko: Gekko Timeseries and Modeling Software for Python
Project-URL: Homepage, https://t-t.dk/gekko
Project-URL: Repository, https://github.com/thomsen67/GekkoTimeseries
Author: Thomas Thomsen
License-Expression: MIT
License-File: LICENCE
Classifier: Operating System :: Microsoft :: Windows
Classifier: Programming Language :: C#
Classifier: Programming Language :: Python :: 3
Requires-Python: <3.14,>=3.11
Requires-Dist: pythonnet<4.0.0,>=3.0.1; sys_platform == 'win32' and platform_machine == 'AMD64'
